ansys/speos/core/__init__.py
ansys/speos/core/body.py
ansys/speos/core/bsdf.py
ansys/speos/core/face.py
ansys/speos/core/geo_ref.py
ansys/speos/core/intensity.py
ansys/speos/core/launcher.py
ansys/speos/core/logger.py
ansys/speos/core/lxp.py
ansys/speos/core/opt_prop.py
ansys/speos/core/part.py
ansys/speos/core/project.py
ansys/speos/core/proto_message_utils.py
ansys/speos/core/py.typed
ansys/speos/core/sensor.py
ansys/speos/core/simulation.py
ansys/speos/core/source.py
ansys/speos/core/spectrum.py
ansys/speos/core/speos.py
ansys/speos/core/generic/constants.py
ansys/speos/core/generic/general_methods.py
ansys/speos/core/generic/visualization_methods.py
ansys/speos/core/kernel/__init__.py
ansys/speos/core/kernel/body.py
ansys/speos/core/kernel/client.py
ansys/speos/core/kernel/crud.py
ansys/speos/core/kernel/face.py
ansys/speos/core/kernel/intensity_template.py
ansys/speos/core/kernel/job.py
ansys/speos/core/kernel/part.py
ansys/speos/core/kernel/proto_message_utils.py
ansys/speos/core/kernel/scene.py
ansys/speos/core/kernel/sensor_template.py
ansys/speos/core/kernel/simulation_template.py
ansys/speos/core/kernel/sop_template.py
ansys/speos/core/kernel/source_template.py
ansys/speos/core/kernel/spectrum.py
ansys/speos/core/kernel/vop_template.py
ansys/speos/core/kernel/grpc/transport_options.py
ansys/speos/core/workflow/__init__.py
ansys/speos/core/workflow/combine_speos.py
ansys/speos/core/workflow/open_result.py
ansys_speos_core-0.7.1.dist-info/licenses/LICENSE
ansys_speos_core-0.7.1.dist-info/WHEEL
ansys_speos_core-0.7.1.dist-info/METADATA
ansys_speos_core-0.7.1.dist-info/RECORD
