Metadata-Version: 2.4
Name: ansys-speos-core
Version: 0.7.1
Summary: A Python wrapper for Ansys Speos
Author-email: "ANSYS, Inc." <pyansys.core@ansys.com>
Maintainer-email: "ANSYS, Inc." <pyansys.core@ansys.com>
Requires-Python: >=3.10
Classifier: Development Status :: 4 - Beta
Classifier: Intended Audience :: Developers
Classifier: Intended Audience :: Science/Research
Classifier: Intended Audience :: Manufacturing
Classifier: License :: OSI Approved :: MIT License
Classifier: Operating System :: OS Independent
Classifier: Programming Language :: Python :: 3.10
Classifier: Programming Language :: Python :: 3.11
Classifier: Programming Language :: Python :: 3.12
Classifier: Programming Language :: Python :: 3.13
Classifier: Topic :: Software Development :: Libraries
Classifier: Topic :: Scientific/Engineering :: Physics
Classifier: Topic :: Scientific/Engineering :: Information Analysis
License-File: LICENSE
Requires-Dist: protobuf>=3.20,<7
Requires-Dist: grpcio>=1.50.0,<1.77
Requires-Dist: grpcio-health-checking>=1.45.0,<1.68
Requires-Dist: ansys-api-speos==0.15.3
Requires-Dist: ansys-tools-common>=0.3.1
Requires-Dist: numpy>=1.20.3,<3
Requires-Dist: comtypes>=1.4,<1.5; platform_system=='Windows'
Requires-Dist: ansys-sphinx-theme[autoapi]==1.6.4 ; extra == "doc"
Requires-Dist: ansys-tools-visualization-interface>=0.8.3 ; extra == "doc"
Requires-Dist: numpydoc==1.10.0 ; extra == "doc"
Requires-Dist: Sphinx==8.1.3 ; extra == "doc"
Requires-Dist: sphinx-copybutton==0.5.2 ; extra == "doc"
Requires-Dist: sphinxcontrib-mermaid==1.2.3 ; extra == "doc"
Requires-Dist: myst-parser==4.0.1 ; extra == "doc"
Requires-Dist: nbsphinx==0.9.8 ; extra == "doc"
Requires-Dist: jupytext==1.18.1 ; extra == "doc"
Requires-Dist: jupyterlab==4.5.1 ; extra == "doc"
Requires-Dist: jupyter-server==2.17.0 ; extra == "doc"
Requires-Dist: nbconvert==7.16.6 ; extra == "doc"
Requires-Dist: pyvista[jupyter]>=0.43,<0.47 ; extra == "doc"
Requires-Dist: pyvista>=0.40.0,<0.47 ; extra == "graphics"
Requires-Dist: ansys-tools-visualization-interface>=0.8.3 ; extra == "graphics"
Requires-Dist: matplotlib ; extra == "jupyter"
Requires-Dist: jupyterlab>=3 ; extra == "jupyter"
Requires-Dist: ipywidgets ; extra == "jupyter"
Requires-Dist: pyvista[jupyter]>=0.43,<0.47 ; extra == "jupyter"
Requires-Dist: ansys-tools-visualization-interface>=0.8.3 ; extra == "jupyter"
Requires-Dist: notebook==7.5.1 ; extra == "jupyter"
Requires-Dist: psutil==7.2.1 ; extra == "tests"
Requires-Dist: pytest==9.0.2 ; extra == "tests"
Requires-Dist: pyvista>=0.40.0,<0.47 ; extra == "tests"
Requires-Dist: ansys-tools-visualization-interface>=0.8.3 ; extra == "tests"
Requires-Dist: ansys-platform-instancemanagement>=1.0.3 ; extra == "tests"
Requires-Dist: pytest-cov==7.0.0 ; extra == "tests"
Project-URL: Changelog, https://github.com/ansys/pyspeos/blob/main/doc/source/changelog.rst
Project-URL: Discussions, https://github.com/ansys/pyspeos/discussions
Project-URL: Documentation, https://speos.docs.pyansys.com/
Project-URL: Issues, https://github.com/ansys/pyspeos/issues
Project-URL: Releases, https://github.com/ansys/pyspeos/releases
Project-URL: Source, https://github.com/ansys/pyspeos
Provides-Extra: doc
Provides-Extra: graphics
Provides-Extra: jupyter
Provides-Extra: tests
